ruler/__init__.py
ruler/base_rules.py
ruler/rules.py
ruler-2.0.0.dist-info/DESCRIPTION.rst
ruler-2.0.0.dist-info/LICENSE.txt
ruler-2.0.0.dist-info/METADATA
ruler-2.0.0.dist-info/RECORD
ruler-2.0.0.dist-info/WHEEL
ruler-2.0.0.dist-info/metadata.json
ruler-2.0.0.dist-info/top_level.txt
