Metadata-Version: 1.1
Name: ruler
Version: 2.0.0
Summary: Humane grammar library
Home-page: https://github.com/yanivmo/ruler
Author: Yaniv Mordekhay
Author-email: yaniv@linuxmail.org
License: MIT
Keywords: regex parsing grammar
Platform: UNKNOWN
Classifier: Development Status :: 5 - Production/Stable
Classifier: License :: OSI Approved :: MIT License
Classifier: Intended Audience :: Developers
Classifier: Operating System :: OS Independent
Classifier: Topic :: Software Development :: Libraries :: Python Modules
Classifier: Programming Language :: Python :: 2
Classifier: Programming Language :: Python :: 2.7
Classifier: Programming Language :: Python :: 3
Classifier: Programming Language :: Python :: 3.3
Classifier: Programming Language :: Python :: 3.4
Classifier: Programming Language :: Python :: 3.5
Classifier: Programming Language :: Python :: 3.6
